calkha_utils/__init__.py
calkha_utils/api_view.py
calkha_utils/base_model.py
calkha_utils/functions.py
calkha_utils/view_base_class.py
calkha_utils-0.1.1.dist-info/METADATA
calkha_utils-0.1.1.dist-info/WHEEL
calkha_utils-0.1.1.dist-info/RECORD
