Metadata-Version: 2.1
Name: calkha-utils
Version: 0.1.1
Summary: Common utilities for django project
Author: Ouattara Aboubacar Sionna
Author-email: sionnaouattara@gmail.com
Requires-Python: >=3.9,<4.0
Classifier: Programming Language :: Python :: 3
Classifier: Programming Language :: Python :: 3.9
Classifier: Programming Language :: Python :: 3.10
Classifier: Programming Language :: Python :: 3.11
Requires-Dist: django-softdelete (>=0.10.5)
Requires-Dist: djangorestframework (>=3.14.0)
